LICENSE
MANIFEST.in
NOTICE
README.txt
setup.py
systemml/__init__.py
systemml/classloader.py
systemml/converters.py
systemml/defmatrix.py
systemml/mlcontext.py
systemml/project_info.py
systemml.egg-info/PKG-INFO
systemml.egg-info/SOURCES.txt
systemml.egg-info/dependency_links.txt
systemml.egg-info/requires.txt
systemml.egg-info/top_level.txt
systemml/mllearn/__init__.py
systemml/mllearn/estimators.py
systemml/mllearn/keras2caffe.py
systemml/random/__init__.py
systemml/random/sampling.py
systemml/systemml-java/systemml-1.1.0-extra.jar
systemml/systemml-java/systemml-1.1.0.jar