Metadata-Version: 1.1
Name: systemml
Version: 1.1.0
Summary: Apache SystemML is a distributed and declarative machine learning platform.
Home-page: http://systemml.apache.org/
Author: Apache SystemML
Author-email: dev@systemml.apache.org
License: Apache 2.0
Platform: UNKNOWN
Classifier: Intended Audience :: Developers
Classifier: Intended Audience :: Education
Classifier: Intended Audience :: Science/Research
Classifier: License :: OSI Approved :: Apache Software License
Classifier: Programming Language :: Python :: 2.7
Classifier: Topic :: Scientific/Engineering :: Mathematics
Classifier: Topic :: Software Development :: Libraries :: Python Modules
Classifier: Topic :: Software Development :: Libraries
